nprime/__init__.py
nprime/plot.py
nprime/pyprime.py
nprime-1.3.1.dist-info/licenses/LICENSE
nprime-1.3.1.dist-info/METADATA
nprime-1.3.1.dist-info/WHEEL
nprime-1.3.1.dist-info/top_level.txt
nprime-1.3.1.dist-info/zip-safe
nprime-1.3.1.dist-info/RECORD
