Metadata-Version: 2.4
Name: nprime
Version: 1.3.1
Summary: Python library for primes algorithms
Home-page: https://github.com/Sylhare/nprime
Author: sylhare
Author-email: sylhare <sylhare@outlook.com>
License: GNU General Public License v3.0
Project-URL: Homepage, https://github.com/Sylhare/nprime
Project-URL: Repository, https://github.com/Sylhare/nprime
Project-URL: Issues, https://github.com/Sylhare/nprime/issues
Keywords: prime,fermat,miller rabin,math
Platform: any
Classifier: Development Status :: 5 - Production/Stable
Classifier: Programming Language :: Python
Classifier: Programming Language :: Python :: 3
Classifier: Programming Language :: Python :: 3.9
Classifier: Programming Language :: Python :: 3.10
Classifier: Programming Language :: Python :: 3.11
Classifier: Programming Language :: Python :: 3.12
Classifier: Programming Language :: Python :: 3.13
Classifier: Programming Language :: Python :: 3 :: Only
Classifier: Environment :: Other Environment
Classifier: Intended Audience :: Developers
Classifier: Intended Audience :: Science/Research
Classifier: Intended Audience :: Education
Classifier: License :: OSI Approved :: GNU Library or Lesser General Public License (LGPL)
Classifier: Operating System :: OS Independent
Classifier: Topic :: Software Development :: Libraries :: Python Modules
Classifier: Topic :: Software Development :: Libraries
Classifier: Topic :: Scientific/Engineering :: Mathematics
Classifier: Topic :: Utilities
Requires-Python: >=3.9
License-File: LICENSE
Requires-Dist: matplotlib>=3.5.0
Dynamic: author
Dynamic: home-page
Dynamic: license-file
Dynamic: platform
